ticklog/__init__.py
ticklog/test.py
ticklog-0.1.0.dist-info/METADATA
ticklog-0.1.0.dist-info/WHEEL
ticklog-0.1.0.dist-info/top_level.txt
ticklog-0.1.0.dist-info/RECORD
